streamlit_antd_components_mod/__init__.py
streamlit_antd_components_mod/frontend/build/asset-manifest.json
streamlit_antd_components_mod/frontend/build/bootstrap.min.css
streamlit_antd_components_mod/frontend/build/index.html
streamlit_antd_components_mod/frontend/build/static/css/2.5f650c68.chunk.css
streamlit_antd_components_mod/frontend/build/static/css/2.5f650c68.chunk.css.map
streamlit_antd_components_mod/frontend/build/static/css/main.7806baf1.chunk.css
streamlit_antd_components_mod/frontend/build/static/css/main.7806baf1.chunk.css.map
streamlit_antd_components_mod/frontend/build/static/js/2.1406deea.chunk.js
streamlit_antd_components_mod/frontend/build/static/js/2.1406deea.chunk.js.LICENSE.txt
streamlit_antd_components_mod/frontend/build/static/js/2.1406deea.chunk.js.map
streamlit_antd_components_mod/frontend/build/static/js/2.e9d6107e.chunk.js
streamlit_antd_components_mod/frontend/build/static/js/2.e9d6107e.chunk.js.LICENSE.txt
streamlit_antd_components_mod/frontend/build/static/js/2.e9d6107e.chunk.js.map
streamlit_antd_components_mod/frontend/build/static/js/main.93c84dd4.chunk.js
streamlit_antd_components_mod/frontend/build/static/js/main.93c84dd4.chunk.js.map
streamlit_antd_components_mod/frontend/build/static/js/main.b0db34a5.chunk.js
streamlit_antd_components_mod/frontend/build/static/js/main.b0db34a5.chunk.js.map
streamlit_antd_components_mod/frontend/build/static/js/main.b7f0479d.chunk.js
streamlit_antd_components_mod/frontend/build/static/js/main.b7f0479d.chunk.js.map
streamlit_antd_components_mod/frontend/build/static/js/main.c2271f12.chunk.js
streamlit_antd_components_mod/frontend/build/static/js/main.c2271f12.chunk.js.map
streamlit_antd_components_mod/frontend/build/static/js/main.f02dbc66.chunk.js
streamlit_antd_components_mod/frontend/build/static/js/main.f02dbc66.chunk.js.map
streamlit_antd_components_mod/frontend/build/static/js/runtime-main.1784c245.js
streamlit_antd_components_mod/frontend/build/static/js/runtime-main.1784c245.js.map
streamlit_antd_components_mod-0.1.7.dist-info/LICENSE
streamlit_antd_components_mod-0.1.7.dist-info/METADATA
streamlit_antd_components_mod-0.1.7.dist-info/WHEEL
streamlit_antd_components_mod-0.1.7.dist-info/top_level.txt
streamlit_antd_components_mod-0.1.7.dist-info/RECORD
