Metadata-Version: 2.1
Name: streamlit-antd-components-mod
Version: 0.1.7
Summary: streamlit custom components of Antd Design and Mantine, modded from jihaoran's streamlit-antd-components
Home-page: https://github.com/Cocopuffff/StreamlitAntdComponents
Author: kennethqzw
Requires-Python: >=3.8
License-File: LICENSE
Requires-Dist: streamlit>=1.12.0
